debuglib/__init__.py
debuglib/__main__.py
debuglib/_packages.py
debuglib/_typing.py
debuglib/defaults.py
debuglib/_cli/__init__.py
debuglib/_cli/debugger/__init__.py
debuglib/_cli/listener/__init__.py
debuglib/_cli/listener/listener.py
debuglib/core/__init__.py
debuglib/core/client/__init__.py
debuglib/core/common/__init__.py
debuglib/core/common/extract_server_info.py
debuglib/core/common/prog.py
debuglib/core/server/__init__.py
debuglib/decorator/__init__.py
debuglib/decorator/_util.py
debuglib/decorator/decorator.py
debuglib/hook/__init__.py
debuglib/hook/_hook.py
debuglib/hook/install.py
debuglib/logging/__init__.py
debuglib/logging/handler.py
debuglib-0.1.0.dist-info/LICENSE
debuglib-0.1.0.dist-info/METADATA
debuglib-0.1.0.dist-info/WHEEL
debuglib-0.1.0.dist-info/entry_points.txt
debuglib-0.1.0.dist-info/top_level.txt
debuglib-0.1.0.dist-info/RECORD
