Metadata-Version: 2.1
Name: debuglib
Version: 0.1.0
Summary: python debugger tool with easy integration into any program
Home-page: https://github.com/utility-libraries/debuglib-py
Author: PlayerG9
License: MIT
Project-URL: Author Github, https://github.com/PlayerG9
Project-URL: Homepage, https://github.com/utility-libraries/debuglib-py
Project-URL: Bug Tracker, https://github.com/utility-libraries/debuglib-py/issues
Classifier: Intended Audience :: Developers
Classifier: License :: OSI Approved :: MIT License
Classifier: Natural Language :: English
Classifier: Operating System :: OS Independent
Classifier: Programming Language :: Python :: 3
Classifier: Programming Language :: Python :: 3 :: Only
Classifier: Programming Language :: Python :: 3.7
Classifier: Programming Language :: Python :: 3.8
Classifier: Programming Language :: Python :: 3.9
Classifier: Programming Language :: Python :: 3.10
Classifier: Programming Language :: Python :: 3.11
Classifier: Programming Language :: Python :: 3.12
Classifier: Programming Language :: Python :: 3.13
Classifier: Topic :: Utilities
Requires-Python: >=3.6
License-File: LICENSE
Provides-Extra: all
Requires-Dist: better-exceptions ; extra == 'all'
Requires-Dist: orjson ; extra == 'all'
Requires-Dist: textual ; extra == 'all'
Provides-Extra: cli
Requires-Dist: textual ; extra == 'cli'
Provides-Extra: dev
Requires-Dist: better-exceptions ; extra == 'dev'
Provides-Extra: orjson
Requires-Dist: orjson ; extra == 'orjson'
